LICENSE
README.md
setup.cfg
setup.py
micropython_iotPervasiveServiceSDK.egg-info/PKG-INFO
micropython_iotPervasiveServiceSDK.egg-info/SOURCES.txt
micropython_iotPervasiveServiceSDK.egg-info/dependency_links.txt
micropython_iotPervasiveServiceSDK.egg-info/requires.txt
micropython_iotPervasiveServiceSDK.egg-info/top_level.txt
serviceSDK/__init__.py
serviceSDK/config.py
serviceSDK/proxySDK.py
serviceSDK/core/applicationContext.py
serviceSDK/core/scheduleService.py
serviceSDK/core/serverInvoker.py
serviceSDK/core/exception/commonException.py
serviceSDK/core/exception/sdkException.py
serviceSDK/core/exception/serviceException.py
serviceSDK/core/job/contextUpLoadJob.py
serviceSDK/core/job/eventListenerJob.py
serviceSDK/core/job/mqttCheckMessageJob.py
serviceSDK/core/job/mqttHealthJob.py
serviceSDK/core/loader/hardwareInfoLoader.py
serviceSDK/core/loader/proxyLoader.py
serviceSDK/core/loader/serversLoader.py
serviceSDK/core/loader/thingProxyFuncLoader.py
serviceSDK/core/sender/baseSender.py
serviceSDK/core/sender/hardwareUpLoadSender.py
serviceSDK/model/elemrntTree/ElementTree.py
serviceSDK/model/elemrntTree/xmltok2.py
serviceSDK/model/microWebSrv/__init__.py
serviceSDK/model/microWebSrv/microWebSocket.py
serviceSDK/model/microWebSrv/microWebSrv.py
serviceSDK/model/microWebSrv/microWebTemplate.py
serviceSDK/model/ujinja/source.py
serviceSDK/ownService/systemEventFactory.py
serviceSDK/ownService/systemServiceFactory.py
serviceSDK/pojo/capabilityBean.py
serviceSDK/pojo/eventBean.py
serviceSDK/pojo/serviceBean.py
serviceSDK/proxy/proxyBase.py
serviceSDK/proxy/pythonServiceProxy.py
serviceSDK/proxy/thingProxy.py
serviceSDK/router/httpRouter.py
serviceSDK/router/mqttRouter.py
serviceSDK/systemService/httpService.py
serviceSDK/systemService/mqttService.py
serviceSDK/systemService/updateService.py
serviceSDK/utils/TimeUtil.py
serviceSDK/utils/copyUtils.py
serviceSDK/utils/fileUtils.py
serviceSDK/utils/logutil.py
serviceSDK/utils/pathUtils.py
serviceSDK/utils/tarGzUtils.py
serviceSDK/utils/taskUtils.py
serviceSDK/utils/templateUtils.py