Metadata-Version: 2.1
Name: micropython-iotPervasiveServiceSDK
Version: 1.0.16
Summary: 设备端直连框架python
Author: whu贾向阳团队-葛家和
Author-email: 2898534520@qq.com
Keywords: micropython
Classifier: Development Status :: 5 - Production/Stable
License-File: LICENSE
